[
  { "slug": "rainbow",                           "name": "Rainbow Pride",                       "group": "umbrella",   "description": "The original LGBTQ+ pride symbol, representing the diversity of the wider queer community." },
  { "slug": "progress-pride",                    "name": "Progress Pride",                      "group": "umbrella",   "description": "A 2018 redesign that adds black, brown, and trans-flag colors to centre people of color and transgender people within the LGBTQ+ community." },
  { "slug": "intersex-inclusive-progress-pride", "name": "Intersex-Inclusive Progress Pride",   "group": "umbrella",   "description": "A 2021 update to the Progress flag that adds a purple-on-yellow ring to also include intersex people." },
  { "slug": "queer",                             "name": "Queer",                               "group": "umbrella",   "description": "An umbrella term used by some people whose gender or sexuality falls outside more specific labels." },

  { "slug": "gay-men-mlm",                       "name": "Gay men (mlm)",                       "group": "attraction", "description": "A man who is romantically or sexually attracted to other men, or more broadly any man-loving-man identity." },
  { "slug": "lesbian",                           "name": "Lesbian",                             "group": "attraction", "description": "A woman who is romantically or sexually attracted to other women." },
  { "slug": "bisexual",                          "name": "Bisexual",                            "group": "attraction", "description": "A person who is attracted to people of more than one gender." },
  { "slug": "pansexual",                         "name": "Pansexual",                           "group": "attraction", "description": "A person who is attracted to people regardless of gender." },
  { "slug": "polysexual",                        "name": "Polysexual",                          "group": "attraction", "description": "A person who is attracted to multiple, but not necessarily all, genders." },
  { "slug": "omnisexual",                        "name": "Omnisexual",                          "group": "attraction", "description": "A person who is attracted to people of all genders, with gender still playing a role in the attraction." },
  { "slug": "asexual",                           "name": "Asexual",                             "group": "attraction", "description": "A person who experiences little to no sexual attraction to others." },
  { "slug": "graysexual",                        "name": "Graysexual",                          "group": "attraction", "description": "A person who experiences sexual attraction rarely or only under specific circumstances." },
  { "slug": "demisexual",                        "name": "Demisexual",                          "group": "attraction", "description": "A person who only experiences sexual attraction after forming a deep emotional bond." },
  { "slug": "aromantic",                         "name": "Aromantic",                           "group": "attraction", "description": "A person who experiences little to no romantic attraction to others." },
  { "slug": "demiromantic",                      "name": "Demiromantic",                        "group": "attraction", "description": "A person who only feels romantic attraction after forming a deep emotional bond." },
  { "slug": "abrosexual",                        "name": "Abrosexual",                          "group": "attraction", "description": "A person whose sexual orientation is fluid and shifts between orientations over time." },
  { "slug": "polyamory",                         "name": "Polyamory",                           "group": "attraction", "description": "The practice of having multiple consensual, loving relationships at the same time, with the knowledge of everyone involved." },

  { "slug": "transgender",                       "name": "Transgender",                         "group": "gender",     "description": "A person whose gender identity differs from the sex they were assigned at birth." },
  { "slug": "nonbinary",                         "name": "Non-binary",                          "group": "gender",     "description": "A person whose gender identity is not exclusively man or woman." },
  { "slug": "genderqueer",                       "name": "Genderqueer",                         "group": "gender",     "description": "A person whose gender identity falls outside or across binary categories of man and woman." },
  { "slug": "genderfluid",                       "name": "Genderfluid",                         "group": "gender",     "description": "A person whose gender identity shifts over time between different gender experiences." },
  { "slug": "agender",                           "name": "Agender",                             "group": "gender",     "description": "A person who does not identify with any gender, or who identifies as gender-neutral." },
  { "slug": "bigender",                          "name": "Bigender",                            "group": "gender",     "description": "A person who identifies as two genders, either simultaneously or alternately." },
  { "slug": "demigender",                        "name": "Demigender",                          "group": "gender",     "description": "A person who feels a partial but not full connection to a particular gender identity." },
  { "slug": "neutrois",                          "name": "Neutrois",                            "group": "gender",     "description": "A person who identifies as having a neutral, null, or absent gender." },
  { "slug": "intersex",                          "name": "Intersex",                            "group": "gender",     "description": "A person born with sex characteristics that don't fit typical definitions of male or female." },
  { "slug": "two-spirit",                        "name": "Two-Spirit",                          "group": "gender",     "description": "An Indigenous North American term for a person who embodies both masculine and feminine spirits within Indigenous traditions." }
]
